snowmate_collector/__init__.py
snowmate_collector/exceptions.py
snowmate_collector/interceptor.cpython-310-darwin.so
snowmate_collector/metrics.py
snowmate_collector/configs/__init__.py
snowmate_collector/configs/collector_settings.py
snowmate_collector/consts/__init__.py
snowmate_collector/consts/api_consts.py
snowmate_collector/consts/data_collection.py
snowmate_collector/consts/logs.py
snowmate_collector/data_collection/__init__.py
snowmate_collector/data_collection/execution_flow.cpython-310-darwin.so
snowmate_collector/data_collection/function_call_data.cpython-310-darwin.so
snowmate_collector/data_collection/function_call_data_collector.cpython-310-darwin.so
snowmate_collector/data_collection/function_metadata_extractor.cpython-310-darwin.so
snowmate_collector/data_collection/metrics.cpython-310-darwin.so
snowmate_collector/data_collection/used_attributes_collector.py
snowmate_collector/data_handling/__init__.py
snowmate_collector/data_handling/function_call_msg_handler.py
snowmate_collector/data_handling/interfaces.py
snowmate_collector/data_handling/metrics_msg_handler.py
snowmate_collector/data_handling/msg_router_subscriber.py
snowmate_collector/data_handling/sub_process_manger.py
snowmate_collector/data_handling/zmq_ipc.py
snowmate_collector/data_handling/msg_parsers/__init__.py
snowmate_collector/data_handling/msg_parsers/function_call_parser.py
snowmate_collector/data_handling/msg_parsers/utils.py
snowmate_collector/data_serialization/__init__.py
snowmate_collector/data_serialization/ipc_serializer.cpython-310-darwin.so
snowmate_collector/data_serialization/ipc_serializer_base.cpython-310-darwin.so
snowmate_collector/data_serialization/pickler.cpython-310-darwin.so
snowmate_collector/data_serialization/snow_pickle.so
snowmate_collector/data_serialization/utils.py
snowmate_collector/data_sink/__init__.py
snowmate_collector/data_sink/debug_file_sink.py
snowmate_collector/data_sink/debug_none_sink.py
snowmate_collector/data_sink/debug_print_sink.py
snowmate_collector-0.0.61.dist-info/LICENSE
snowmate_collector-0.0.61.dist-info/METADATA
snowmate_collector-0.0.61.dist-info/WHEEL
snowmate_collector-0.0.61.dist-info/top_level.txt
snowmate_collector-0.0.61.dist-info/RECORD
